sanic_base_ext/__init__.py
sanic_base_extension-0.1.1.dist-info/DESCRIPTION.rst
sanic_base_extension-0.1.1.dist-info/METADATA
sanic_base_extension-0.1.1.dist-info/RECORD
sanic_base_extension-0.1.1.dist-info/WHEEL
sanic_base_extension-0.1.1.dist-info/metadata.json
sanic_base_extension-0.1.1.dist-info/top_level.txt
