Metadata-Version: 2.0
Name: sanic-base-extension
Version: 0.1.1
Summary: Flask-like extension support for Sanic framework
Home-page: https://github.com/Relrin/sanic-base-extension
Author: Valeryi Savich
Author-email: relrin78@gmail.com
License: BSD
Platform: any
Classifier: Environment :: Web Environment
Classifier: License :: OSI Approved :: BSD License
Classifier: Intended Audience :: Developers
Classifier: Operating System :: OS Independent
Classifier: Programming Language :: Python
Classifier: Programming Language :: Python :: 3
Classifier: Programming Language :: Python :: 3.5
Classifier: Programming Language :: Python :: 3.6
Classifier: Programming Language :: Python :: 3.7
Classifier: Programming Language :: Python :: Implementation :: CPython
Classifier: Topic :: Software Development :: Libraries :: Python Modules
